{"stat.killEntity.Skeleton":13,"stat.walkOneCm":45093,"achievement.openInventory":9,"stat.leaveGame":7,"stat.damageTaken":325,"stat.mobKills":16,"stat.useItem.minecraft.golden_apple":4,"stat.flyOneCm":54641,"stat.jump":258,"stat.playOneMinute":11061,"stat.fallOneCm":9393,"stat.useItem.minecraft.stone_sword":41,"stat.killEntity.Villager":3,"stat.damageDealt":3430,"stat.timeSinceDeath":11061,"stat.sprintOneCm":26711,"stat.useItem.minecraft.spawn_egg":20,"achievement.exploreAllBiomes":{"value":0,"progress":["Desert"]}}